codebrix/__init__.py
codebrix/math.py
codebrix/utils.py
codebrix-0.3.0.dist-info/METADATA
codebrix-0.3.0.dist-info/WHEEL
codebrix-0.3.0.dist-info/top_level.txt
codebrix-0.3.0.dist-info/RECORD
