Metadata-Version: 2.4
Name: codebrix
Version: 0.3.0
Summary: Nur lokal verwendetes Beispielprojekt
Author: Lars Erler
